tests/__init__.py
tests/test_hashtag.py
tiktok_collector/__init__.py
tiktok_collector/brand.py
tiktok_collector/hashtag.py
tiktok_collector/keyword.py
tiktok_collector/post_comment.py
tiktok_collector/post_detail.py
tiktok_collector/post_recent.py
tiktok_collector/threads_keyword.py
tiktok_collector/threads_post_comment.py
tiktok_collector/user.py
tiktok_collector/utils.py
tiktok_collector-0.6.7.dist-info/licenses/LICENSE
tiktok_collector-0.6.7.dist-info/METADATA
tiktok_collector-0.6.7.dist-info/WHEEL
tiktok_collector-0.6.7.dist-info/top_level.txt
tiktok_collector-0.6.7.dist-info/RECORD
