Metadata-Version: 2.4
Name: tiktok-collector
Version: 0.6.7
Summary: A Python library for collecting TikTok data
Home-page: https://github.com/yourusername/tiktok-collector
Author: Dong Hoang
Author-email: donghoang@example.com
Classifier: Programming Language :: Python :: 3
Classifier: License :: OSI Approved :: MIT License
Classifier: Operating System :: OS Independent
Requires-Python: >=3.7
License-File: LICENSE
Requires-Dist: requests>=2.25.1
Requires-Dist: pandas>=1.2.0
Requires-Dist: numpy>=1.19.0
Requires-Dist: python-dotenv>=0.19.0
Requires-Dist: boto3>=1.26.0
Requires-Dist: pytz>=2021.1
Requires-Dist: httplib2>=0.20.0
Requires-Dist: sqlalchemy>=1.4.0
Requires-Dist: openpyxl>=3.1.0
Requires-Dist: pyspark>=3.3.0
Dynamic: author
Dynamic: author-email
Dynamic: classifier
Dynamic: description
Dynamic: description-content-type
Dynamic: home-page
Dynamic: license-file
Dynamic: requires-dist
Dynamic: requires-python
Dynamic: summary
